projest/__init__.py
projest/aminoacid.py
projest/atom.py
projest/chain.py
projest/extract_atoms_information.py
projest/model.py
projest/protein.py
projest/test.py
projest-0.0.7.dist-info/LICENSE.txt
projest-0.0.7.dist-info/METADATA
projest-0.0.7.dist-info/WHEEL
projest-0.0.7.dist-info/top_level.txt
projest-0.0.7.dist-info/RECORD
