Metadata-Version: 2.1
Name: projest
Version: 0.0.7
Summary: A small example package
Home-page: https://github.com/sthhher/projest
Author: Esther Vendrell
Author-email: esvemira@hotmail.com
License: UNKNOWN
Platform: UNKNOWN
Classifier: Programming Language :: Python :: 3
Classifier: License :: OSI Approved :: MIT License
Classifier: Operating System :: OS Independent
